{
  "partner": [
    {
      "id": 1,
      "title": "Directo"
    },
    {
      "id": 2,
      "title": "Obligatorio"
    },
    {
      "id": 3,
      "title": "Convenio"
    },
    {
      "id": 4,
      "title": "Monotributo"
    }
  ],
  "planes": [
    {
      "id": 1,
      "title": "6030"
    },
    {
      "id": 2,
      "title": "110"
    },
    {
      "id": 3,
      "title": "210"
    },
    {
      "id": 4,
      "title": "310"
    },
    {
      "id": 5,
      "title": "410"
    },
    {
      "id": 6,
      "title": "450"
    },
    {
      "id": 7,
      "title": "510"
    }
  ],
  "filiales": [
    {
      "id": 1,
      "title": "filial 1"
    },
    {
      "id": 2,
      "title": "filial 2"
    },
    {
      "id": 3,
      "title": "filial 3"
    },
    {
      "id": 4,
      "title": "filial 4"
    },
    {
      "id": 5,
      "title": "filial 5"
    }
  ],
  "tipoSocio":"M",
    "filialDesc":"Metropolitana",
    "capDesc":"ADMINISTRACION CENTRAL",
    "fechaValorizacion":"2022-04-26",
    "tipoDescuento":"01",
    "listaCotizacionesyProyecciones":[
       {
          "tipoCotizacion":"C",
          "fechaCotizacion":"2022-04-26",
          "datosEtiqueta":{
             "idGrupoFamiliar":"MAT00",
             "descrGrupoFamiliar":"Matrimonio",
             "fechaDesdeLista":"2022-04-01",
             "fechaHastaLista":"2022-04-30",
             "totalAdicionales":0,
             "totalHijoMayor21":0,
             "totalHijoMayor26":0,
             "descrGrupoFamiliarCompleta":"Matrimonio",
             "explicacionGrupoFamiliar":"Titular y cónyuge o conviviente, de los que el mayor de ambos tenga a partir de 36 años de edad."
          },
          "listaCotizaciones":[
             {
                "prefijoPlanCotizado":2,
                "planCotizado":210,
                "valorPlanCotizado":38156.56,
                "aportesPlanCotizado":3195.32,
                "Diferencia":34961.24,
                "moneda":"ARS",
                "bonificacionEspecial":0,
                "cotizacionPorIntegrante":[
                   {
                      "valorPlanCotizado":22933.03,
                      "precioBonificado":0,
                      "nombre":"JUAN",
                      "apellido":"PEREZ",
                      "edad":"059",
                      "relacionFamiliar":"01",
                      "moneda":""
                   },
                   {
                      "valorPlanCotizado":15223.53,
                      "precioBonificado":0,
                      "nombre":"JUANA",
                      "apellido":"SUAREZ",
                      "edad":"051",
                      "relacionFamiliar":"02",
                      "moneda":""
                   }
                ]
             },
             {
                "prefijoPlanCotizado":2,
                "planCotizado":310,
                "valorPlanCotizado":49147.51,
                "aportesPlanCotizado":3195.32,
                "Diferencia":45952.19,
                "moneda":"ARS",
                "bonificacionEspecial":0,
                "cotizacionPorIntegrante":[
                   {
                      "valorPlanCotizado":29606.33,
                      "precioBonificado":0,
                      "nombre":"JUAN",
                      "apellido":"PEREZ",
                      "edad":"059",
                      "relacionFamiliar":"01",
                      "moneda":""
                   },
                   {
                      "valorPlanCotizado":19541.18,
                      "precioBonificado":0,
                      "nombre":"JUANA",
                      "apellido":"SUAREZ",
                      "edad":"051",
                      "relacionFamiliar":"02",
                      "moneda":""
                   }
                ]
             },
             {
                "prefijoPlanCotizado":2,
                "planCotizado":410,
                "valorPlanCotizado":63950.23,
                "aportesPlanCotizado":3195.32,
                "Diferencia":60754.91,
                "moneda":"ARS",
                "bonificacionEspecial":0,
                "cotizacionPorIntegrante":[
                   {
                      "valorPlanCotizado":37924.89,
                      "precioBonificado":0,
                      "nombre":"JUAN",
                      "apellido":"PEREZ",
                      "edad":"059",
                      "relacionFamiliar":"01",
                      "moneda":""
                   },
                   {
                      "valorPlanCotizado":26025.34,
                      "precioBonificado":0,
                      "nombre":"JUANA",
                      "apellido":"SUAREZ",
                      "edad":"051",
                      "relacionFamiliar":"02",
                      "moneda":""
                   }
                ]
             }
          ]
       },
       {
          "tipoCotizacion":"P",
          "fechaCotizacion":"2027-05-01",
          "datosEtiqueta":{
             "idGrupoFamiliar":"MUD00",
             "descrGrupoFamiliar":"Matrimonio 1SRD",
             "fechaDesdeLista":"2022-04-01",
             "fechaHastaLista":"2022-04-30",
             "totalAdicionales":0,
             "totalHijoMayor21":0,
             "totalHijoMayor26":0,
             "descrGrupoFamiliarCompleta":"Matrimonio 1SRD Individual SR Descuento:37,50 %",
             "explicacionGrupoFamiliar":""
          },
          "listaCotizaciones":[
             {
                "prefijoPlanCotizado":2,
                "planCotizado":210,
                "valorPlanCotizado":72615.72,
                "aportesPlanCotizado":3195.32,
                "Diferencia":"69420.40",
                "moneda":"ARS",
                "bonificacionEspecial":0,
                "cotizacionPorIntegrante":[
                   {
                      "valorPlanCotizado":57384.04,
                      "precioBonificado":0,
                      "nombre":"JUAN",
                      "apellido":"PEREZ",
                      "edad":"059",
                      "relacionFamiliar":"01",
                      "moneda":""
                   },
                   {
                      "valorPlanCotizado":15231.68,
                      "precioBonificado":0,
                      "nombre":"JUANA",
                      "apellido":"SUAREZ",
                      "edad":"051",
                      "relacionFamiliar":"02",
                      "moneda":""
                   }
                ]
             },
             {
                "prefijoPlanCotizado":2,
                "planCotizado":310,
                "valorPlanCotizado":93647.06,
                "aportesPlanCotizado":3195.32,
                "Diferencia":90451.74,
                "moneda":"ARS",
                "bonificacionEspecial":0,
                "cotizacionPorIntegrante":[
                   {
                      "valorPlanCotizado":74072.39,
                      "precioBonificado":0,
                      "nombre":"JUAN",
                      "apellido":"PEREZ",
                      "edad":"059",
                      "relacionFamiliar":"01",
                      "moneda":""
                   },
                   {
                      "valorPlanCotizado":19574.67,
                      "precioBonificado":0,
                      "nombre":"JUANA",
                      "apellido":"SUAREZ",
                      "edad":"051",
                      "relacionFamiliar":"02",
                      "moneda":""
                   }
                ]
             },
             {
                "prefijoPlanCotizado":2,
                "planCotizado":410,
                "valorPlanCotizado":120892.65,
                "aportesPlanCotizado":3195.32,
                "Diferencia":117697.33,
                "moneda":"ARS",
                "bonificacionEspecial":0,
                "cotizacionPorIntegrante":[
                   {
                      "valorPlanCotizado":94877.26,
                      "precioBonificado":0,
                      "nombre":"JUAN",
                      "apellido":"PEREZ",
                      "edad":"059",
                      "relacionFamiliar":"01",
                      "moneda":""
                   },
                   {
                      "valorPlanCotizado":26015.39,
                      "precioBonificado":0,
                      "nombre":"JUANA",
                      "apellido":"SUAREZ",
                      "edad":"051",
                      "relacionFamiliar":"02",
                      "moneda":""
                   }
                ]
             }
          ]
       },
       {
          "tipoCotizacion":"P",
          "fechaCotizacion":"2030-05-01",
          "datosEtiqueta":{
             "idGrupoFamiliar":"M2R00",
             "descrGrupoFamiliar":"Matrimonio SRD2",
             "fechaDesdeLista":"2022-04-01",
             "fechaHastaLista":"2022-04-30",
             "totalAdicionales":0,
             "totalHijoMayor21":0,
             "totalHijoMayor26":0,
             "descrGrupoFamiliarCompleta":"Matrimonio SRD2 Individual SR Descuento:37,50 % Cónyuge SR Descuento:60,00 %",
             "explicacionGrupoFamiliar":""
          },
          "listaCotizaciones":[
             {
                "prefijoPlanCotizado":2,
                "planCotizado":210,
                "valorPlanCotizado":94109.83,
                "aportesPlanCotizado":3195.32,
                "Diferencia":90914.51,
                "moneda":"ARS",
                "bonificacionEspecial":0,
                "cotizacionPorIntegrante":[
                   {
                      "valorPlanCotizado":57384.04,
                      "precioBonificado":0,
                      "nombre":"JUAN",
                      "apellido":"PEREZ",
                      "edad":"059",
                      "relacionFamiliar":"01",
                      "moneda":""
                   },
                   {
                      "valorPlanCotizado":36725.79,
                      "precioBonificado":0,
                      "nombre":"JUANA",
                      "apellido":"SUAREZ",
                      "edad":"051",
                      "relacionFamiliar":"02",
                      "moneda":""
                   }
                ]
             },
             {
                "prefijoPlanCotizado":2,
                "planCotizado":310,
                "valorPlanCotizado":121478.72,
                "aportesPlanCotizado":3195.32,
                "Diferencia":"118283.40",
                "moneda":"ARS",
                "bonificacionEspecial":0,
                "cotizacionPorIntegrante":[
                   {
                      "valorPlanCotizado":74072.39,
                      "precioBonificado":0,
                      "nombre":"JUAN",
                      "apellido":"PEREZ",
                      "edad":"059",
                      "relacionFamiliar":"01",
                      "moneda":""
                   },
                   {
                      "valorPlanCotizado":47406.33,
                      "precioBonificado":0,
                      "nombre":"JUANA",
                      "apellido":"SUAREZ",
                      "edad":"051",
                      "relacionFamiliar":"02",
                      "moneda":""
                   }
                ]
             },
             {
                "prefijoPlanCotizado":2,
                "planCotizado":410,
                "valorPlanCotizado":"155598.70",
                "aportesPlanCotizado":3195.32,
                "Diferencia":152403.38,
                "moneda":"ARS",
                "bonificacionEspecial":0,
                "cotizacionPorIntegrante":[
                   {
                      "valorPlanCotizado":94877.26,
                      "precioBonificado":0,
                      "nombre":"JUAN",
                      "apellido":"PEREZ",
                      "edad":"059",
                      "relacionFamiliar":"01",
                      "moneda":""
                   },
                   {
                      "valorPlanCotizado":60721.44,
                      "precioBonificado":0,
                      "nombre":"JUANA",
                      "apellido":"SUAREZ",
                      "edad":"051",
                      "relacionFamiliar":"02",
                      "moneda":""
                   }
                ]
             }
          ]
       }
    ]
}
